Metadata-Version: 2.1
Name: ximilar-client
Version: 1.39.0
Summary: The Ximilar App and Vize.ai Client.
Home-page: https://gitlab.com/ximilar-public/ximilar-vize-api
Author: Michal Lukac, David Novak and Ximilar.com Team
Author-email: tech@ximilar.com
License: Apache 2.0
Keywords: machine learning,multimedia,json,rest,data
Platform: UNKNOWN
Classifier: Development Status :: 3 - Alpha
Classifier: Programming Language :: Python :: 3.9
Classifier: Topic :: Scientific/Engineering :: Artificial Intelligence
License-File: LICENSE
Requires-Dist: requests>=2.23.0
Requires-Dist: pytest>=3.0.3
Requires-Dist: tqdm>=4.31.1
Requires-Dist: urllib3>=1.25.9
